[
  {
    "id": "841c17ff-1d17-4f83-af78-03af17886730",
    "data": [
      {
        "text": "fait-il assez beau à ",
        "userDefined": false
      },
      {
        "text": "Nantes",
        "alias": "address",
        "meta": "@sys.location",
        "userDefined": true
      },
      {
        "text": " pour faire du ",
        "userDefined": false
      },
      {
        "text": "jogging",
        "alias": "activity",
        "meta": "@activity",
        "userDefined": true
      }
    ],
    "isTemplate": false,
    "count": 0,
    "updated": 0
  },
  {
    "id": "a4781bdd-74b2-4766-a266-619c48903ea7",
    "data": [
      {
        "text": "est-ce que ",
        "userDefined": false
      },
      {
        "text": "c",
        "meta": "@sys.ignore",
        "userDefined": false
      },
      {
        "text": "\u0027est le bon temps pour ",
        "userDefined": false
      },
      {
        "text": "faire du vélo",
        "alias": "activity",
        "meta": "@activity",
        "userDefined": false
      },
      {
        "text": " maintenant",
        "userDefined": false
      }
    ],
    "isTemplate": false,
    "count": 0,
    "updated": 0
  },
  {
    "id": "145433cc-face-4231-89b1-ef6cdb57ab58",
    "data": [
      {
        "text": "fait-il beau pour aller ",
        "userDefined": false
      },
      {
        "text": "faire de la luge",
        "alias": "activity",
        "meta": "@activity",
        "userDefined": true
      },
      {
        "text": " ",
        "userDefined": false
      },
      {
        "text": "aujourd\u0027hui",
        "alias": "date-time",
        "meta": "@sys.date-time",
        "userDefined": true
      }
    ],
    "isTemplate": false,
    "count": 1,
    "updated": 0
  },
  {
    "id": "fc6080c4-4874-4576-9b33-493b267a8d7f",
    "data": [
      {
        "text": "le temps est-il assez bon pour faire ",
        "userDefined": false
      },
      {
        "text": "de",
        "meta": "@sys.ignore",
        "userDefined": false
      },
      {
        "text": " ",
        "userDefined": false
      },
      {
        "text": "la",
        "meta": "@sys.ignore",
        "userDefined": false
      },
      {
        "text": " ",
        "userDefined": false
      },
      {
        "text": "marche",
        "alias": "activity",
        "meta": "@activity",
        "userDefined": true
      }
    ],
    "isTemplate": false,
    "count": 0,
    "updated": 0
  },
  {
    "id": "a76db796-0818-40db-9e01-9403f061d110",
    "data": [
      {
        "text": "fera-t-il assez chaud pour aller ",
        "userDefined": false
      },
      {
        "text": "nager",
        "alias": "activity",
        "meta": "@activity",
        "userDefined": true
      },
      {
        "text": " ",
        "userDefined": false
      },
      {
        "text": "demain",
        "alias": "date-time",
        "meta": "@sys.date-time",
        "userDefined": true
      }
    ],
    "isTemplate": false,
    "count": 0,
    "updated": 0
  },
  {
    "id": "23426ae0-cfb8-4277-911d-0f605a631fa0",
    "data": [
      {
        "text": "pourrai-je ",
        "userDefined": false
      },
      {
        "text": "faire du vélo",
        "alias": "activity",
        "meta": "@activity",
        "userDefined": false
      },
      {
        "text": " ",
        "userDefined": false
      },
      {
        "text": "aujourd\u0027hui",
        "alias": "date-time",
        "meta": "@sys.date-time",
        "userDefined": true
      }
    ],
    "isTemplate": false,
    "count": 0,
    "updated": 0
  },
  {
    "id": "30d8bdd1-e481-4584-8ca8-bf3950f462a4",
    "data": [
      {
        "text": "dois-je aller faire de la ",
        "userDefined": false
      },
      {
        "text": "marche",
        "alias": "activity",
        "meta": "@activity",
        "userDefined": false
      }
    ],
    "isTemplate": false,
    "count": 0,
    "updated": 0
  },
  {
    "id": "cc1433cc-c642-4115-91bb-909e5fcaf718",
    "data": [
      {
        "text": "le temps est-il bon pour faire de la ",
        "userDefined": false
      },
      {
        "text": "marche",
        "alias": "activity",
        "meta": "@activity",
        "userDefined": true
      }
    ],
    "isTemplate": false,
    "count": 1,
    "updated": 0
  },
  {
    "id": "7d803d77-22c7-4e1e-91b2-3cbb5f842b8e",
    "data": [
      {
        "text": "fait-il bon pour faire du ",
        "userDefined": false
      },
      {
        "text": "sport",
        "alias": "activity",
        "meta": "@activity",
        "userDefined": true
      },
      {
        "text": " déhors ",
        "userDefined": false
      },
      {
        "text": "aujourd\u0027hui",
        "alias": "date-time",
        "meta": "@sys.date-time",
        "userDefined": true
      }
    ],
    "isTemplate": false,
    "count": 0,
    "updated": 0
  },
  {
    "id": "dcc3a970-e7d6-4387-ab62-ea0fbba0dfa1",
    "data": [
      {
        "text": "fait-il assez beau pour jouer au ",
        "userDefined": false
      },
      {
        "text": "frisbee",
        "alias": "activity",
        "meta": "@activity",
        "userDefined": false
      },
      {
        "text": " dehors",
        "userDefined": false
      }
    ],
    "isTemplate": false,
    "count": 0,
    "updated": 0
  },
  {
    "id": "9e5e20bb-3845-4f5e-9dac-73308e569c18",
    "data": [
      {
        "text": "est-ce qu\u0027",
        "userDefined": false
      },
      {
        "text": "il",
        "meta": "@sys.ignore",
        "userDefined": false
      },
      {
        "text": " fait assez beau pour faire du ",
        "userDefined": false
      },
      {
        "text": "yoga",
        "alias": "activity",
        "meta": "@activity",
        "userDefined": false
      },
      {
        "text": " dehors",
        "userDefined": false
      }
    ],
    "isTemplate": false,
    "count": 0,
    "updated": 0
  },
  {
    "id": "26051177-e0c6-44a6-83e8-bedec2d2e27a",
    "data": [
      {
        "text": "fait-il beau à ",
        "userDefined": false
      },
      {
        "text": "Nantes",
        "alias": "address",
        "meta": "@sys.location",
        "userDefined": true
      },
      {
        "text": " pour faire du ",
        "userDefined": false
      },
      {
        "text": "jogging",
        "alias": "activity",
        "meta": "@activity",
        "userDefined": true
      }
    ],
    "isTemplate": false,
    "count": 0,
    "updated": 0
  },
  {
    "id": "aa3d6e85-31eb-44d4-9b24-8d0548775692",
    "data": [
      {
        "text": "sera-t-il assez chaud pour aller ",
        "userDefined": false
      },
      {
        "text": "nager",
        "alias": "activity",
        "meta": "@activity",
        "userDefined": true
      },
      {
        "text": " ",
        "userDefined": false
      },
      {
        "text": "demain",
        "alias": "date-time",
        "meta": "@sys.date-time",
        "userDefined": true
      }
    ],
    "isTemplate": false,
    "count": 1,
    "updated": 0
  },
  {
    "id": "7516bec2-d7bf-4eb5-adc1-53af1b3db66c",
    "data": [
      {
        "text": "est-ce qu\u0027",
        "userDefined": false
      },
      {
        "text": "il",
        "meta": "@sys.ignore",
        "userDefined": false
      },
      {
        "text": " fera assez ",
        "userDefined": false
      },
      {
        "text": "froid",
        "meta": "@sys.ignore",
        "userDefined": false
      },
      {
        "text": " pour ",
        "userDefined": false
      },
      {
        "text": "faire du snowboard",
        "alias": "activity",
        "meta": "@activity",
        "userDefined": false
      }
    ],
    "isTemplate": false,
    "count": 0,
    "updated": 0
  },
  {
    "id": "6f8b730c-8c77-4bba-a5dd-c6b10479e6de",
    "data": [
      {
        "text": "puis-je sortir pour faire du ",
        "userDefined": false
      },
      {
        "text": "jogging",
        "alias": "activity",
        "meta": "@activity",
        "userDefined": false
      },
      {
        "text": " ",
        "userDefined": false
      },
      {
        "text": "aujourd\u0027hui",
        "alias": "date-time",
        "meta": "@sys.date-time",
        "userDefined": false
      },
      {
        "text": " à ",
        "userDefined": false
      },
      {
        "text": "Paris",
        "alias": "address",
        "meta": "@sys.location",
        "userDefined": false
      }
    ],
    "isTemplate": false,
    "count": 0,
    "updated": 0
  },
  {
    "id": "017a18ba-09bb-4157-b9b0-7899b227c74e",
    "data": [
      {
        "text": "est-ce qu\u0027il fait beau pour faire du ",
        "userDefined": false
      },
      {
        "text": "yoga",
        "alias": "activity",
        "meta": "@activity",
        "userDefined": true
      },
      {
        "text": " dehors",
        "userDefined": false
      }
    ],
    "isTemplate": false,
    "count": 1,
    "updated": 0
  },
  {
    "id": "4561787a-7fdd-453f-8ed6-9bb7d6b49ef6",
    "data": [
      {
        "text": "est-ce qu\u0027il fera froid pour faire du ",
        "userDefined": false
      },
      {
        "text": "snowboard",
        "alias": "activity",
        "meta": "@activity",
        "userDefined": true
      }
    ],
    "isTemplate": false,
    "count": 0,
    "updated": 0
  },
  {
    "id": "5a5435cc-6e49-472f-aa45-c3d2435286d7",
    "data": [
      {
        "text": "est-ce une bonne idée de partir en ",
        "userDefined": false
      },
      {
        "text": "randonnée",
        "alias": "activity",
        "meta": "@activity",
        "userDefined": true
      },
      {
        "text": " maintenant",
        "userDefined": false
      }
    ],
    "isTemplate": false,
    "count": 0,
    "updated": 0
  },
  {
    "id": "7991bff5-ae9d-4275-a9db-fbbafbacdd75",
    "data": [
      {
        "text": "fait-il assez bon pour faire du sport dehors ",
        "userDefined": false
      },
      {
        "text": "aujourd\u0027hui",
        "alias": "date-time",
        "meta": "@sys.date-time",
        "userDefined": true
      }
    ],
    "isTemplate": false,
    "count": 0,
    "updated": 0
  },
  {
    "id": "24fa63c5-2dbf-4d5c-8bca-2d118d4f655b",
    "data": [
      {
        "text": "fait-il assez beau pour aller ",
        "userDefined": false
      },
      {
        "text": "faire de la luge",
        "alias": "activity",
        "meta": "@activity",
        "userDefined": false
      },
      {
        "text": " ",
        "userDefined": false
      },
      {
        "text": "aujourd\u0027hui",
        "alias": "date-time",
        "meta": "@sys.date-time",
        "userDefined": true
      }
    ],
    "isTemplate": false,
    "count": 0,
    "updated": 0
  }
]