[
  {
    "id": "0a84cd20-0fae-4ec3-9435-ca0377e65228",
    "data": [
      {
        "text": "沈陽",
        "alias": "address",
        "meta": "@sys.address",
        "userDefined": false
      },
      {
        "text": "五天後",
        "alias": "date-time",
        "meta": "@sys.date-time",
        "userDefined": false
      }
    ],
    "isTemplate": false,
    "count": 0,
    "updated": 0
  },
  {
    "id": "bfc35eb6-1892-4bdc-8b4c-8fde445b7be9",
    "data": [
      {
        "text": "我要",
        "userDefined": false
      },
      {
        "text": "上海",
        "alias": "address",
        "meta": "@sys.address",
        "userDefined": false
      },
      {
        "text": "明天",
        "alias": "date-time",
        "meta": "@sys.date-time",
        "userDefined": false
      },
      {
        "text": "的",
        "userDefined": false
      }
    ],
    "isTemplate": false,
    "count": 0,
    "updated": 0
  },
  {
    "id": "64af0a2e-b7b2-4820-a2ce-f97314cab639",
    "data": [
      {
        "text": "明天",
        "alias": "date-time",
        "meta": "@sys.date-time",
        "userDefined": false
      },
      {
        "text": "在",
        "userDefined": false
      },
      {
        "text": "北京",
        "alias": "address",
        "meta": "@sys.address",
        "userDefined": false
      }
    ],
    "isTemplate": false,
    "count": 0,
    "updated": 0
  },
  {
    "id": "8a3be7c8-4c58-4564-b1c0-059888164b4d",
    "data": [
      {
        "text": "下星期一",
        "alias": "date-time",
        "meta": "@sys.date-time",
        "userDefined": false
      },
      {
        "text": "在",
        "userDefined": false
      },
      {
        "text": "北京",
        "alias": "address",
        "meta": "@sys.address",
        "userDefined": false
      },
      {
        "text": "呢",
        "userDefined": false
      }
    ],
    "isTemplate": false,
    "count": 0,
    "updated": 0
  },
  {
    "id": "b386c9ba-d891-459e-8a02-6455ae7f5223",
    "data": [
      {
        "text": "還要",
        "userDefined": false
      },
      {
        "text": "下星期日",
        "alias": "date-time",
        "meta": "@sys.date-time",
        "userDefined": true
      },
      {
        "text": "在",
        "userDefined": false
      },
      {
        "text": "蘇州",
        "alias": "address",
        "meta": "@sys.address",
        "userDefined": false
      }
    ],
    "isTemplate": false,
    "count": 0,
    "updated": 0
  },
  {
    "id": "3cc6c6d2-2475-430d-9ed2-aad6e38ac27b",
    "data": [
      {
        "text": "關于",
        "userDefined": false
      },
      {
        "text": "兩天後",
        "alias": "date-time",
        "meta": "@sys.date-time",
        "userDefined": true
      },
      {
        "text": "在",
        "userDefined": false
      },
      {
        "text": "上海",
        "alias": "address",
        "meta": "@sys.address",
        "userDefined": false
      }
    ],
    "isTemplate": false,
    "count": 0,
    "updated": 0
  },
  {
    "id": "3f49b747-79d9-4f00-a6d7-fae32c9cdebe",
    "data": [
      {
        "text": "三天後",
        "alias": "date-time",
        "meta": "@sys.date-time",
        "userDefined": false
      },
      {
        "text": "在",
        "userDefined": false
      },
      {
        "text": "武漢",
        "alias": "address",
        "meta": "@sys.address",
        "userDefined": false
      },
      {
        "text": "呢",
        "userDefined": false
      }
    ],
    "isTemplate": false,
    "count": 0,
    "updated": 0
  },
  {
    "id": "1bf7ff17-7def-479f-b5ed-92b3e27aae1e",
    "data": [
      {
        "text": "下個星期五",
        "alias": "date-time",
        "meta": "@sys.date-time",
        "userDefined": false
      },
      {
        "text": "在",
        "userDefined": false
      },
      {
        "text": "南京",
        "alias": "address",
        "meta": "@sys.address",
        "userDefined": false
      }
    ],
    "isTemplate": false,
    "count": 0,
    "updated": 0
  },
  {
    "id": "c72714ce-2766-449c-ab7d-7e7c0ca5b028",
    "data": [
      {
        "text": "今天",
        "alias": "date-time",
        "meta": "@sys.date-time",
        "userDefined": false
      },
      {
        "text": "在",
        "userDefined": false
      },
      {
        "text": "天津",
        "alias": "address",
        "meta": "@sys.address",
        "userDefined": false
      }
    ],
    "isTemplate": false,
    "count": 0,
    "updated": 0
  },
  {
    "id": "8272a2e0-e161-4ec2-be95-b795ccaf3c44",
    "data": [
      {
        "text": "青島",
        "alias": "address",
        "meta": "@sys.address",
        "userDefined": false
      },
      {
        "text": "明天",
        "alias": "date-time",
        "meta": "@sys.date-time",
        "userDefined": false
      }
    ],
    "isTemplate": false,
    "count": 0,
    "updated": 0
  }
]