[
  {
    "id": "5efadc4e-65c4-4a98-bcac-f8a51ca7efa6",
    "data": [
      {
        "text": "我還很想",
        "userDefined": false
      },
      {
        "text": "一月一號",
        "alias": "date-time",
        "meta": "@sys.date-time",
        "userDefined": false
      }
    ],
    "isTemplate": false,
    "count": 0,
    "updated": 0
  },
  {
    "id": "62f6a7fa-ba8f-47bc-ab84-9141055c9278",
    "data": [
      {
        "text": "還能不能",
        "userDefined": false
      },
      {
        "text": "明天",
        "alias": "date-time",
        "meta": "@sys.date-time",
        "userDefined": false
      }
    ],
    "isTemplate": false,
    "count": 0,
    "updated": 0
  },
  {
    "id": "d56e3eaf-07b0-4fdf-ada5-aa433c87f5ee",
    "data": [
      {
        "text": "現在",
        "userDefined": false
      },
      {
        "text": "明天",
        "alias": "date-time",
        "meta": "@sys.date-time",
        "userDefined": false
      }
    ],
    "isTemplate": false,
    "count": 0,
    "updated": 0
  },
  {
    "id": "8449df74-fc00-4af8-9109-50f5b683f790",
    "data": [
      {
        "text": "會不會",
        "userDefined": false
      },
      {
        "text": "前天",
        "alias": "date-time",
        "meta": "@sys.date-time",
        "userDefined": false
      }
    ],
    "isTemplate": false,
    "count": 0,
    "updated": 0
  },
  {
    "id": "4fc280a1-2a50-461b-82fc-87f9f18efd6a",
    "data": [
      {
        "text": "還要",
        "userDefined": false
      },
      {
        "text": "明天",
        "alias": "date-time",
        "meta": "@sys.date-time",
        "userDefined": false
      }
    ],
    "isTemplate": false,
    "count": 0,
    "updated": 0
  },
  {
    "id": "ec8ff384-861e-4863-ba01-cb1096a80954",
    "data": [
      {
        "text": "還需要",
        "userDefined": false
      },
      {
        "text": "昨天",
        "alias": "date-time",
        "meta": "@sys.date-time",
        "userDefined": false
      }
    ],
    "isTemplate": false,
    "count": 0,
    "updated": 0
  },
  {
    "id": "481b57ad-c3b7-454b-a2bc-24a583d89361",
    "data": [
      {
        "text": "關于",
        "userDefined": false
      },
      {
        "text": "兩天後",
        "alias": "date-time",
        "meta": "@sys.date-time",
        "userDefined": true
      }
    ],
    "isTemplate": false,
    "count": 0,
    "updated": 0
  },
  {
    "id": "ea1fdd9f-c4fe-4bb2-a850-35735f1d3ecf",
    "data": [
      {
        "text": "關",
        "meta": "@sys.ignore",
        "userDefined": false
      },
      {
        "text": "于",
        "userDefined": false
      },
      {
        "text": "明天",
        "alias": "date-time",
        "meta": "@sys.date-time",
        "userDefined": false
      }
    ],
    "isTemplate": false,
    "count": 0,
    "updated": 0
  },
  {
    "id": "d36d4e06-34d2-4d7c-ade2-68c540c605b8",
    "data": [
      {
        "text": "能不能",
        "userDefined": false
      },
      {
        "text": "下星期五",
        "alias": "date-time",
        "meta": "@sys.date-time",
        "userDefined": false
      }
    ],
    "isTemplate": false,
    "count": 0,
    "updated": 0
  },
  {
    "id": "342edc3e-c963-49c5-8753-19d45598f849",
    "data": [
      {
        "text": "怎麽能",
        "userDefined": false
      },
      {
        "text": "下個星期日",
        "alias": "date-time",
        "meta": "@sys.date-time",
        "userDefined": false
      }
    ],
    "isTemplate": false,
    "count": 0,
    "updated": 0
  },
  {
    "id": "aaf568ed-4972-4f6c-b0c9-f8bfd4681215",
    "data": [
      {
        "text": "明天",
        "alias": "date-time",
        "meta": "@sys.date-time",
        "userDefined": false
      }
    ],
    "isTemplate": false,
    "count": 0,
    "updated": 0
  },
  {
    "id": "71b70e9f-5661-49cc-9875-ab125f96e139",
    "data": [
      {
        "text": "我還要",
        "userDefined": false
      },
      {
        "text": "昨天",
        "alias": "date-time",
        "meta": "@sys.date-time",
        "userDefined": false
      }
    ],
    "isTemplate": false,
    "count": 0,
    "updated": 0
  },
  {
    "id": "b59393e6-b449-4550-8300-df1b5a8efbf4",
    "data": [
      {
        "text": "還要",
        "userDefined": false
      },
      {
        "text": "三天前",
        "alias": "date-time",
        "meta": "@sys.date-time",
        "userDefined": false
      }
    ],
    "isTemplate": false,
    "count": 0,
    "updated": 0
  }
]